LICENSE
MANIFEST.in
README.md
setup.cfg
setup.py
mkpdfs_mkdocs/__init__.py
mkpdfs_mkdocs/generator.py
mkpdfs_mkdocs/mkpdfs.py
mkpdfs_mkdocs/utils.py
mkpdfs_mkdocs.egg-info/PKG-INFO
mkpdfs_mkdocs.egg-info/SOURCES.txt
mkpdfs_mkdocs.egg-info/dependency_links.txt
mkpdfs_mkdocs.egg-info/entry_points.txt
mkpdfs_mkdocs.egg-info/not-zip-safe
mkpdfs_mkdocs.egg-info/requires.txt
mkpdfs_mkdocs.egg-info/top_level.txt
mkpdfs_mkdocs/design/FiraSans-Bold.otf
mkpdfs_mkdocs/design/FiraSans-Italic.otf
mkpdfs_mkdocs/design/FiraSans-Light.otf
mkpdfs_mkdocs/design/FiraSans-LightItalic.otf
mkpdfs_mkdocs/design/FiraSans-Regular.otf
mkpdfs_mkdocs/design/cover.jpg
mkpdfs_mkdocs/design/fonts/font-awesome.css
mkpdfs_mkdocs/design/fonts/material-icons.css
mkpdfs_mkdocs/design/fonts/specimen/FontAwesome.ttf
mkpdfs_mkdocs/design/fonts/specimen/FontAwesome.woff
mkpdfs_mkdocs/design/fonts/specimen/FontAwesome.woff2
mkpdfs_mkdocs/design/fonts/specimen/MaterialIcons-Regular.ttf
mkpdfs_mkdocs/design/fonts/specimen/MaterialIcons-Regular.woff
mkpdfs_mkdocs/design/fonts/specimen/MaterialIcons-Regular.woff2
mkpdfs_mkdocs/preprocessor/__init__.py
mkpdfs_mkdocs/preprocessor/prep.py
mkpdfs_mkdocs/preprocessor/links/__init__.py
mkpdfs_mkdocs/preprocessor/links/transform.py
mkpdfs_mkdocs/preprocessor/links/util.py