Metadata-Version: 2.1
Name: mkpdfs-mkdocs
Version: 1.0.0
Summary: Allows the generation of the PDF version of your MkDocs documentation.
Home-page: https://mkpdfs.comwes.eu
Author: Comwes
Author-email: contact@comwes.eu
Maintainer: Gerry Ntabuhashe
Maintainer-email: gnt@comwes.eu
License: GPLv3
Project-URL: Bug Reports, https://github.com/comwes/mkpdfs-mkdocs-plugin/issues
Project-URL: Source, https://github.com/comwes/mkpdfs-mkdocs-plugin
Keywords: mkdocs documentation pdf export weasyprint markdown plugin
Platform: UNKNOWN
Classifier: Development Status :: 4 - Beta
Classifier: Intended Audience :: Developers
Classifier: Intended Audience :: Education
Classifier: Intended Audience :: Information Technology
Classifier: Intended Audience :: System Administrators
Classifier: License :: OSI Approved :: GNU General Public License v3 (GPLv3)
Classifier: Topic :: Documentation
Classifier: Topic :: Printing
Classifier: Programming Language :: Other
Classifier: Programming Language :: Python
Classifier: Programming Language :: Python :: 3 :: Only
Classifier: Programming Language :: Python :: 3.4
Classifier: Programming Language :: Python :: 3.5
Classifier: Programming Language :: Python :: 3.6
Classifier: Programming Language :: Python :: 3.7
Requires-Python: >=3.4
